thompson/__init__.py
thompson/examples.py
thompson/thompson.py
thompson/data/ads_data.zip
thompson-1.1.0.dist-info/licenses/LICENSE
thompson-1.1.0.dist-info/METADATA
thompson-1.1.0.dist-info/WHEEL
thompson-1.1.0.dist-info/top_level.txt
thompson-1.1.0.dist-info/RECORD
