Metadata-Version: 2.4
Name: thompson
Version: 1.1.0
Summary: The multi-armed bandit by Thompson Sampling, UCB-Upper confidence Bound, and randomized sampling.
Author-email: Erdogan Taskesen <erdogant@gmail.com>
License: MIT License
Project-URL: Homepage, https://erdogant.github.io/thompson
Project-URL: Download, https://github.com/erdogant/thompson/archive/{version}.tar.gz
Keywords: Python,Thompson,multi-armed bandit,UCB-Upper confidence Bound,randomized sampling
Classifier: Programming Language :: Python :: 3
Classifier: License :: OSI Approved :: MIT License
Classifier: Operating System :: OS Independent
Requires-Python: >=3
License-File: LICENSE
Requires-Dist: matplotlib
Requires-Dist: numpy
Requires-Dist: pandas
Requires-Dist: requests
Dynamic: license-file
